nonebot_plugin_small_world/__init__.py
nonebot_plugin_small_world/name2id.py
nonebot_plugin_small_world/data/cards.json
nonebot_plugin_small_world-0.1.1.dist-info/METADATA
nonebot_plugin_small_world-0.1.1.dist-info/WHEEL
nonebot_plugin_small_world-0.1.1.dist-info/top_level.txt
nonebot_plugin_small_world-0.1.1.dist-info/RECORD
