Metadata-Version: 2.1
Name: nonebot-plugin-small-world
Version: 0.1.1
Requires-Dist: nonebot2
Requires-Dist: nonebot-adapter-onebot
